[{"actor":"鳳ここな","actorRomanization":"Otori Kokona","attribute":"彩属性","fullName":"【シリウス】鳳ここな","id":"110010","name":"シリウス","num":1,"rarity":1},{"actor":"静香","actorRomanization":" Shizuka","attribute":"凛属性","fullName":"【シリウス】静香","id":"110020","name":"シリウス","num":1,"rarity":1},{"actor":"カトリナ・グリーベル","actorRomanization":"Kathrina Griebel","attribute":"陽属性","fullName":"【シリウス】カトリナ・グリーベル","id":"110030","name":"シリウス","num":1,"rarity":1},{"actor":"新妻八恵","actorRomanization":"Niizuma Yae","attribute":"彩属性","fullName":"【シリウス】新妻八恵","id":"110040","name":"シリウス","num":1,"rarity":1},{"actor":"柳場ぱんだ","actorRomanization":"Yanagiba Panda","attribute":"陽属性","fullName":"【シリウス】柳場ぱんだ","id":"110050","name":"シリウス","num":1,"rarity":1},{"actor":"流石知冴","actorRomanization":"Sasuga Chisa","attribute":"憐属性","fullName":"【シリウス】流石知冴","id":"110060","name":"シリウス","num":1,"rarity":1},{"actor":"連尺野初魅","actorRomanization":"Renjakuno Hatsumi","attribute":"凛属性","fullName":"【Eden】連尺野初魅","id":"110070","name":"Eden","num":1,"rarity":1},{"actor":"烏森大黒","actorRomanization":"Karasumori Daikoku","attribute":"彩属性","fullName":"【Eden】烏森大黒","id":"110080","name":"Eden","num":1,"rarity":1},{"actor":"舎人仁花子","actorRomanization":"Toneri Nikako","attribute":"陽属性","fullName":"【Eden】舎人仁花子","id":"110090","name":"Eden","num":1,"rarity":1},{"actor":"萬容","actorRomanization":"Yorozu Iruru","attribute":"陽属性","fullName":"【Eden】萬容","id":"110100","name":"Eden","num":1,"rarity":1},{"actor":"筆島しぐれ","actorRomanization":"Fudeshima Shigure","attribute":"憐属性","fullName":"【Eden】筆島しぐれ","id":"110110","name":"Eden","num":1,"rarity":1},{"actor":"千寿暦","actorRomanization":"Senju Koyomi","attribute":"凛属性","fullName":"【銀河座】千寿暦","id":"110120","name":"銀河座","num":1,"rarity":1},{"actor":"ラモーナ・ウォルフ","actorRomanization":"Ramona Wolf","attribute":"凛属性","fullName":"【銀河座】ラモーナ・ウォルフ","id":"110130","name":"銀河座","num":1,"rarity":1},{"actor":"王雪","actorRomanization":"Wang Xue","attribute":"憐属性","fullName":"【銀河座】王雪","id":"110140","name":"銀河座","num":1,"rarity":1},{"actor":"リリヤ・クルトベイ","actorRomanization":"Lilja Kurtbay","attribute":"彩属性","fullName":"【銀河座】リリヤ・クルトベイ","id":"110150","name":"銀河座","num":1,"rarity":1},{"actor":"与那国緋花里","actorRomanization":"Yonaguni Hikari","attribute":"陽属性","fullName":"【銀河座】与那国緋花里","id":"110160","name":"銀河座","num":1,"rarity":1},{"actor":"千寿いろは","actorRomanization":"Senju Iroha","attribute":"憐属性","fullName":"【劇団電姫】千寿いろは","id":"110170","name":"劇団電姫","num":1,"rarity":1},{"actor":"白丸美兎","actorRomanization":"Shiromaru Mito","attribute":"彩属性","fullName":"【劇団電姫】白丸美兎","id":"110180","name":"劇団電姫","num":1,"rarity":1},{"actor":"阿岐留カミラ","actorRomanization":"Akiru Kamira","attribute":"陽属性","fullName":"【劇団電姫】阿岐留カミラ","id":"110190","name":"劇団電姫","num":1,"rarity":1},{"actor":"猫足蕾","actorRomanization":"Nekoashi Tsubomi","attribute":"凛属性","fullName":"【劇団電姫】猫足蕾","id":"110200","name":"劇団電姫","num":1,"rarity":1},{"actor":"本巣叶羽","actorRomanization":"Motosu Towa","attribute":"憐属性","fullName":"【劇団電姫】本巣叶羽","id":"110210","name":"劇団電姫","num":1,"rarity":1},{"actor":"鳳ここな","actorRomanization":"Otori Kokona","attribute":"凛属性","fullName":"【夢見る少女】鳳ここな","id":"120010","name":"夢見る少女","num":1,"rarity":2},{"actor":"静香","actorRomanization":" Shizuka","attribute":"彩属性","fullName":"【シリウスのツッコミ】静香","id":"120020","name":"シリウスのツッコミ","num":1,"rarity":2},{"actor":"カトリナ・グリーベル","actorRomanization":"Kathrina Griebel","attribute":"憐属性","fullName":"【ワールドダイスターの愛娘】カトリナ・グリーベル","id":"120030","name":"ワールドダイスターの愛娘","num":1,"rarity":2},{"actor":"新妻八恵","actorRomanization":"Niizuma Yae","attribute":"陽属性","fullName":"【天使系小学生】新妻八恵","id":"120040","name":"天使系小学生","num":1,"rarity":2},{"actor":"柳場ぱんだ","actorRomanization":"Yanagiba Panda","attribute":"憐属性","fullName":"【腹黒計算ガール】柳場ぱんだ","id":"120050","name":"腹黒計算ガール","num":1,"rarity":2},{"actor":"流石知冴","actorRomanization":"Sasuga Chisa","attribute":"彩属性","fullName":"【シリウスの秘密兵器】流石知冴","id":"120060","name":"シリウスの秘密兵器","num":1,"rarity":2},{"actor":"連尺野初魅","actorRomanization":"Renjakuno Hatsumi","attribute":"彩属性","fullName":"【覇道の天才】連尺野初魅","id":"120070","name":"覇道の天才","num":1,"rarity":2},{"actor":"烏森大黒","actorRomanization":"Karasumori Daikoku","attribute":"陽属性","fullName":"【愛憎まみれる乙女】烏森大黒","id":"120080","name":"愛憎まみれる乙女","num":1,"rarity":2},{"actor":"舎人仁花子","actorRomanization":"Toneri Nikako","attribute":"憐属性","fullName":"【純真無垢な少女】舎人仁花子","id":"120090","name":"純真無垢な少女","num":1,"rarity":2},{"actor":"萬容","actorRomanization":"Yorozu Iruru","attribute":"憐属性","fullName":"【下町のアイドル】萬容","id":"120100","name":"下町のアイドル","num":1,"rarity":2},{"actor":"筆島しぐれ","actorRomanization":"Fudeshima Shigure","attribute":"凛属性","fullName":"【小悪魔系小学生】筆島しぐれ","id":"120110","name":"小悪魔系小学生","num":1,"rarity":2},{"actor":"千寿暦","actorRomanization":"Senju Koyomi","attribute":"彩属性","fullName":"【名家の姉】千寿暦","id":"120120","name":"名家の姉","num":1,"rarity":2},{"actor":"ラモーナ・ウォルフ","actorRomanization":"Ramona Wolf","attribute":"彩属性","fullName":"【世話好き優等生】ラモーナ・ウォルフ","id":"120130","name":"世話好き優等生","num":1,"rarity":2},{"actor":"王雪","actorRomanization":"Wang Xue","attribute":"凛属性","fullName":"【勝気な倹約家】王雪","id":"120140","name":"勝気な倹約家","num":1,"rarity":2},{"actor":"リリヤ・クルトベイ","actorRomanization":"Lilja Kurtbay","attribute":"陽属性","fullName":"【白銀の美少女】リリヤ・クルトベイ","id":"120150","name":"白銀の美少女","num":1,"rarity":2},{"actor":"与那国緋花里","actorRomanization":"Yonaguni Hikari","attribute":"憐属性","fullName":"【元気いっぱいダンサー】与那国緋花里","id":"120160","name":"元気いっぱいダンサー","num":1,"rarity":2},{"actor":"千寿いろは","actorRomanization":"Senju Iroha","attribute":"凛属性","fullName":"【オタクでお嬢様】千寿いろは","id":"120170","name":"オタクでお嬢様","num":1,"rarity":2},{"actor":"白丸美兎","actorRomanization":"Shiromaru Mito","attribute":"陽属性","fullName":"【内気な孝行娘】白丸美兎","id":"120180","name":"内気な孝行娘","num":1,"rarity":2},{"actor":"阿岐留カミラ","actorRomanization":"Akiru Kamira","attribute":"憐属性","fullName":"【悟り系ギャル】阿岐留カミラ","id":"120190","name":"悟り系ギャル","num":1,"rarity":2},{"actor":"猫足蕾","actorRomanization":"Nekoashi Tsubomi","attribute":"彩属性","fullName":"【電姫の占い師】猫足蕾","id":"120200","name":"電姫の占い師","num":1,"rarity":2},{"actor":"本巣叶羽","actorRomanization":"Motosu Towa","attribute":"凛属性","fullName":"【ぐーたら好きの天才子役】本巣叶羽","id":"120210","name":"ぐーたら好きの天才子役","num":1,"rarity":2},{"actor":"鳳ここな","actorRomanization":"Otori Kokona","attribute":"陽属性","fullName":"【役者としての成長】鳳ここな","id":"130010","name":"役者としての成長","num":1,"rarity":3},{"actor":"静香","actorRomanization":" Shizuka","attribute":"陽属性","fullName":"【一番風呂のために】静香","id":"130020","name":"一番風呂のために","num":1,"rarity":3},{"actor":"カトリナ・グリーベル","actorRomanization":"Kathrina Griebel","attribute":"凛属性","fullName":"【砕けたガラスは……】カトリナ・グリーベル","id":"130030","name":"砕けたガラスは……","num":1,"rarity":3},{"actor":"新妻八恵","actorRomanization":"Niizuma Yae","attribute":"陽属性","fullName":"【思い出に花を咲かせて】新妻八恵","id":"130040","name":"思い出に花を咲かせて","num":1,"rarity":3},{"actor":"柳場ぱんだ","actorRomanization":"Yanagiba Panda","attribute":"凛属性","fullName":"【トレンドは生活風景】柳場ぱんだ","id":"130050","name":"トレンドは生活風景","num":1,"rarity":3},{"actor":"流石知冴","actorRomanization":"Sasuga Chisa","attribute":"彩属性","fullName":"【見てしまった……】流石知冴","id":"130060","name":"見てしまった……","num":1,"rarity":3},{"actor":"連尺野初魅","actorRomanization":"Renjakuno Hatsumi","attribute":"陽属性","fullName":"【新たな日常】連尺野初魅","id":"130070","name":"新たな日常","num":1,"rarity":3},{"actor":"烏森大黒","actorRomanization":"Karasumori Daikoku","attribute":"憐属性","fullName":"【恨みをつづって】烏森大黒","id":"130080","name":"恨みをつづって","num":1,"rarity":3},{"actor":"舎人仁花子","actorRomanization":"Toneri Nikako","attribute":"彩属性","fullName":"【都会ってすごい！】舎人仁花子","id":"130090","name":"都会ってすごい！","num":1,"rarity":3},{"actor":"萬容","actorRomanization":"Yorozu Iruru","attribute":"凛属性","fullName":"【ここいらでひとつ、大勝負】萬容","id":"130100","name":"ここいらでひとつ、大勝負","num":1,"rarity":3},{"actor":"筆島しぐれ","actorRomanization":"Fudeshima Shigure","attribute":"憐属性","fullName":"【体育なんて滅びちゃえ！】筆島しぐれ","id":"130110","name":"体育なんて滅びちゃえ！","num":1,"rarity":3},{"actor":"千寿暦","actorRomanization":"Senju Koyomi","attribute":"陽属性","fullName":"【お嬢様のオフタイム】千寿暦","id":"130120","name":"お嬢様のオフタイム","num":1,"rarity":3},{"actor":"ラモーナ・ウォルフ","actorRomanization":"Ramona Wolf","attribute":"凛属性","fullName":"【世話焼きは果てしなく】ラモーナ・ウォルフ","id":"130130","name":"世話焼きは果てしなく","num":1,"rarity":3},{"actor":"王雪","actorRomanization":"Wang Xue","attribute":"彩属性","fullName":"【あるのは勝ちだけ】王雪","id":"130140","name":"あるのは勝ちだけ","num":1,"rarity":3},{"actor":"リリヤ・クルトベイ","actorRomanization":"Lilja Kurtbay","attribute":"憐属性","fullName":"【自然な一日】リリヤ・クルトベイ","id":"130150","name":"自然な一日","num":1,"rarity":3},{"actor":"与那国緋花里","actorRomanization":"Yonaguni Hikari","attribute":"凛属性","fullName":"【踊ればなんくるない！】与那国緋花里","id":"130160","name":"踊ればなんくるない！","num":1,"rarity":3},{"actor":"千寿いろは","actorRomanization":"Senju Iroha","attribute":"彩属性","fullName":"【来ちゃいました！】千寿いろは","id":"130170","name":"来ちゃいました！","num":1,"rarity":3},{"actor":"白丸美兎","actorRomanization":"Shiromaru Mito","attribute":"憐属性","fullName":"【まさかのお客様】白丸美兎","id":"130180","name":"まさかのお客様","num":1,"rarity":3},{"actor":"阿岐留カミラ","actorRomanization":"Akiru Kamira","attribute":"凛属性","fullName":"【新作お菓子レビュー】阿岐留カミラ","id":"130190","name":"新作お菓子レビュー","num":1,"rarity":3},{"actor":"猫足蕾","actorRomanization":"Nekoashi Tsubomi","attribute":"陽属性","fullName":"【悪鬼退散っ！】猫足蕾","id":"130200","name":"悪鬼退散っ！","num":1,"rarity":3},{"actor":"本巣叶羽","actorRomanization":"Motosu Towa","attribute":"彩属性","fullName":"【先輩の本気】本巣叶羽","id":"130210","name":"先輩の本気","num":1,"rarity":3},{"actor":"萬容","actorRomanization":"Yorozu Iruru","attribute":"憐属性","fullName":"【頼れる先輩】萬容","id":"130220","name":"頼れる先輩","num":1,"rarity":3},{"actor":"千寿いろは","actorRomanization":"Senju Iroha","attribute":"凛属性","fullName":"【最後はBBQ！】千寿いろは","id":"130230","name":"最後はBBQ！","num":1,"rarity":3},{"actor":"流石知冴","actorRomanization":"Sasuga Chisa","attribute":"凛属性","fullName":"【流石の釣り名人】流石知冴","id":"130240","name":"流石の釣り名人","num":1,"rarity":3},{"actor":"ラモーナ・ウォルフ","actorRomanization":"Ramona Wolf","attribute":"彩属性","fullName":"【手に入れたいのは……】ラモーナ・ウォルフ","id":"130250","name":"手に入れたいのは……","num":1,"rarity":3},{"actor":"猫足蕾","actorRomanization":"Nekoashi Tsubomi","attribute":"憐属性","fullName":"【水晶玉に映る未来】猫足蕾","id":"130260","name":"水晶玉に映る未来","num":1,"rarity":3},{"actor":"鳳ここな","actorRomanization":"Otori Kokona","attribute":"彩属性","fullName":"【負けられない一戦】鳳ここな","id":"130270","name":"負けられない一戦","num":1,"rarity":3},{"actor":"千寿いろは","actorRomanization":"Senju Iroha","attribute":"陽属性","fullName":"【お姉ちゃんが心配です】千寿いろは","id":"130280","name":"お姉ちゃんが心配です","num":1,"rarity":3},{"actor":"阿岐留カミラ","actorRomanization":"Akiru Kamira","attribute":"凛属性","fullName":"【ほら、帰ろ？】阿岐留カミラ","id":"130290","name":"ほら、帰ろ？","num":1,"rarity":3},{"actor":"柳場ぱんだ","actorRomanization":"Yanagiba Panda","attribute":"憐属性","fullName":"【ぱんだ with パンダ！】柳場ぱんだ","id":"130300","name":"ぱんだ with パンダ！","num":1,"rarity":3},{"actor":"本巣叶羽","actorRomanization":"Motosu Towa","attribute":"彩属性","fullName":"【仲間のために】本巣叶羽","id":"130310","name":"仲間のために","num":1,"rarity":3},{"actor":"与那国緋花里","actorRomanization":"Yonaguni Hikari","attribute":"凛属性","fullName":"【ん～っ！　デリシャス！】与那国緋花里","id":"130320","name":"ん～っ！　デリシャス！","num":1,"rarity":3},{"actor":"新妻八恵","actorRomanization":"Niizuma Yae","attribute":"陽属性","fullName":"【いっしょに遊びませんか？】新妻八恵","id":"130330","name":"いっしょに遊びませんか？","num":1,"rarity":3},{"actor":"連尺野初魅","actorRomanization":"Renjakuno Hatsumi","attribute":"彩属性","fullName":"【その目をよく見せてくれ】連尺野初魅","id":"130340","name":"その目をよく見せてくれ","num":1,"rarity":3},{"actor":"カトリナ・グリーベル","actorRomanization":"Kathrina Griebel","attribute":"陽属性","fullName":"【ファントムの面影を宿す天才】カトリナ・グリーベル","id":"130350","name":"ファントムの面影を宿す天才","num":1,"rarity":3},{"actor":"白丸美兎","actorRomanization":"Shiromaru Mito","attribute":"憐属性","fullName":"【ど、どどど、どうしよう！】白丸美兎","id":"130360","name":"ど、どどど、どうしよう！","num":1,"rarity":3},{"actor":"千寿暦","actorRomanization":"Senju Koyomi","attribute":"陽属性","fullName":"【さあ、どうぞ】千寿暦","id":"130370","name":"さあ、どうぞ","num":1,"rarity":3},{"actor":"静香","actorRomanization":" Shizuka","attribute":"憐属性","fullName":"【開運は実力よね！】静香","id":"130380","name":"開運は実力よね！","num":1,"rarity":3},{"actor":"烏森大黒","actorRomanization":"Karasumori Daikoku","attribute":"凛属性","fullName":"【しょうがないわね】烏森大黒","id":"130390","name":"しょうがないわね","num":1,"rarity":3},{"actor":"新妻八恵","actorRomanization":"Niizuma Yae","attribute":"彩属性","fullName":"【口いっぱいに広がる海の味】新妻八恵","id":"130400","name":"口いっぱいに広がる海の味","num":1,"rarity":3},{"actor":"筆島しぐれ","actorRomanization":"Fudeshima Shigure","attribute":"凛属性","fullName":"【どれにしようかな？】筆島しぐれ","id":"130420","name":"どれにしようかな？","num":1,"rarity":3},{"actor":"白丸美兎","actorRomanization":"Shiromaru Mito","attribute":"陽属性","fullName":"【みんなが大切だからこそ】白丸美兎","id":"130430","name":"みんなが大切だからこそ","num":1,"rarity":3},{"actor":"柳場ぱんだ","actorRomanization":"Yanagiba Panda","attribute":"凛属性","fullName":"【言うだけタダですし！】柳場ぱんだ","id":"130450","name":"言うだけタダですし！","num":1,"rarity":3},{"actor":"舎人仁花子","actorRomanization":"Toneri Nikako","attribute":"憐属性","fullName":"【おずおずスクロール】舎人仁花子","id":"130460","name":"おずおずスクロール","num":1,"rarity":3},{"actor":"王雪","actorRomanization":"Wang Xue","attribute":"彩属性","fullName":"【伝統料理で勝負だ！】王雪","id":"130470","name":"伝統料理で勝負だ！","num":1,"rarity":3},{"actor":"カトリナ・グリーベル","actorRomanization":"Kathrina Griebel","attribute":"憐属性","fullName":"【別に心配なんか……】カトリナ・グリーベル","id":"130480","name":"別に心配なんか……","num":1,"rarity":3},{"actor":"リリヤ・クルトベイ","actorRomanization":"Lilja Kurtbay","attribute":"彩属性","fullName":"【リラックス・ナイト・タイム】リリヤ・クルトベイ","id":"130490","name":"リラックス・ナイト・タイム","num":1,"rarity":3},{"actor":"連尺野初魅","actorRomanization":"Renjakuno Hatsumi","attribute":"陽属性","fullName":"【勝手なことは許さない】連尺野初魅","id":"130500","name":"勝手なことは許さない","num":1,"rarity":3},{"actor":"静香","actorRomanization":" Shizuka","attribute":"彩属性","fullName":"【3分だけだからね！】静香","id":"130510","name":"3分だけだからね！","num":1,"rarity":3},{"actor":"流石知冴","actorRomanization":"Sasuga Chisa","attribute":"凛属性","fullName":"【雨上がりを演じて】流石知冴","id":"130520","name":"雨上がりを演じて","num":1,"rarity":3},{"actor":"千寿暦","actorRomanization":"Senju Koyomi","attribute":"彩属性","fullName":"【食べちゃうぞ～！】千寿暦","id":"130530","name":"食べちゃうぞ～！","num":1,"rarity":3},{"actor":"阿岐留カミラ","actorRomanization":"Akiru Kamira","attribute":"陽属性","fullName":"【友達なのに／だから】阿岐留カミラ","id":"130540","name":"友達なのに／だから","num":1,"rarity":3},{"actor":"猫足蕾","actorRomanization":"Nekoashi Tsubomi","attribute":"憐属性","fullName":"【踏みにじられた者の怒り】猫足蕾","id":"130550","name":"踏みにじられた者の怒り","num":1,"rarity":3},{"actor":"本巣叶羽","actorRomanization":"Motosu Towa","attribute":"陽属性","fullName":"【フラワー・テンペスト】本巣叶羽","id":"130560","name":"フラワー・テンペスト","num":1,"rarity":3},{"actor":"与那国緋花里","actorRomanization":"Yonaguni Hikari","attribute":"凛属性","fullName":"【茜染め・世界征服】与那国緋花里","id":"130570","name":"茜染め・世界征服","num":1,"rarity":3},{"actor":"烏森大黒","actorRomanization":"Karasumori Daikoku","attribute":"憐属性","fullName":"【私よりふさわしい人】烏森大黒","id":"130580","name":"私よりふさわしい人","num":1,"rarity":3},{"actor":"ラモーナ・ウォルフ","actorRomanization":"Ramona Wolf","attribute":"凛属性","fullName":"【小指をからめて】ラモーナ・ウォルフ","id":"130590","name":"小指をからめて","num":1,"rarity":3},{"actor":"舎人仁花子","actorRomanization":"Toneri Nikako","attribute":"彩属性","fullName":"【本日晴天、プール日和】舎人仁花子","id":"130600","name":"本日晴天、プール日和","num":1,"rarity":3},{"actor":"萬容","actorRomanization":"Yorozu Iruru","attribute":"凛属性","fullName":"【ゆらゆらリラクゼーション】萬容","id":"130610","name":"ゆらゆらリラクゼーション","num":1,"rarity":3},{"actor":"鳳ここな","actorRomanization":"Otori Kokona","attribute":"陽属性","fullName":"【ひとくちシェアしよう？】鳳ここな","id":"130620","name":"ひとくちシェアしよう？","num":1,"rarity":3},{"actor":"王雪","actorRomanization":"Wang Xue","attribute":"陽属性","fullName":"【合理的なアドバイス】王雪","id":"130630","name":"合理的なアドバイス","num":1,"rarity":3},{"actor":"千寿いろは","actorRomanization":"Senju Iroha","attribute":"憐属性","fullName":"【お団子と放課後と】千寿いろは","id":"130640","name":"お団子と放課後と","num":1,"rarity":3},{"actor":"ラモーナ・ウォルフ","actorRomanization":"Ramona Wolf","attribute":"彩属性","fullName":"【グレートリッパー・オーダー】ラモーナ・ウォルフ","id":"130650","name":"グレートリッパー・オーダー","num":1,"rarity":3},{"actor":"新妻八恵","actorRomanization":"Niizuma Yae","attribute":"凛属性","fullName":"【お話、聞きましょうか？】新妻八恵","id":"130660","name":"お話、聞きましょうか？","num":1,"rarity":3},{"actor":"与那国緋花里","actorRomanization":"Yonaguni Hikari","attribute":"憐属性","fullName":"【美味しいはシェアしないと！】与那国緋花里","id":"130670","name":"美味しいはシェアしないと！","num":1,"rarity":3},{"actor":"筆島しぐれ","actorRomanization":"Fudeshima Shigure","attribute":"憐属性","fullName":"【一番大事にすべきもの】筆島しぐれ","id":"130680","name":"一番大事にすべきもの","num":1,"rarity":3},{"actor":"柳場ぱんだ","actorRomanization":"Yanagiba Panda","attribute":"凛属性","fullName":"【きゃー、こわーい！】柳場ぱんだ","id":"130690","name":"きゃー、こわーい！","num":1,"rarity":3},{"actor":"柳場ぱんだ","actorRomanization":"Yanagiba Panda","attribute":"彩属性","fullName":"【社長業もおしゃまにね！】柳場ぱんだ","id":"130700","name":"社長業もおしゃまにね！","num":1,"rarity":3},{"actor":"連尺野初魅","actorRomanization":"Renjakuno Hatsumi","attribute":"凛属性","fullName":"【何度でも熱く、自由に】連尺野初魅","id":"130710","name":"何度でも熱く、自由に","num":1,"rarity":3},{"actor":"千寿暦","actorRomanization":"Senju Koyomi","attribute":"凛属性","fullName":"【いつもと違うわたくし】千寿暦","id":"130720","name":"いつもと違うわたくし","num":1,"rarity":3},{"actor":"萬容","actorRomanization":"Yorozu Iruru","attribute":"陽属性","fullName":"【ぴったりなプレゼントを探して】萬容","id":"130730","name":"ぴったりなプレゼントを探して","num":1,"rarity":3},{"actor":"流石知冴","actorRomanization":"Sasuga Chisa","attribute":"凛属性","fullName":"【尾行、キタキツネのように】流石知冴","id":"130740","name":"尾行、キタキツネのように","num":1,"rarity":3},{"actor":"舎人仁花子","actorRomanization":"Toneri Nikako","attribute":"彩属性","fullName":"【あつあつ、いただきます】舎人仁花子","id":"130750","name":"あつあつ、いただきます","num":1,"rarity":3},{"actor":"静香","actorRomanization":" Shizuka","attribute":"憐属性","fullName":"【マスカレイドな恋愛劇】静香","id":"130760","name":"マスカレイドな恋愛劇","num":1,"rarity":3},{"actor":"王雪","actorRomanization":"Wang Xue","attribute":"陽属性","fullName":"【とろける極楽気分】王雪","id":"130770","name":"とろける極楽気分","num":1,"rarity":3},{"actor":"新妻八恵","actorRomanization":"Niizuma Yae","attribute":"憐属性","fullName":"【素敵な思い、受け取りました！】新妻八恵","id":"130780","name":"素敵な思い、受け取りました！","num":1,"rarity":3},{"actor":"王雪","actorRomanization":"Wang Xue","attribute":"陽属性","fullName":"【得意のセールストーク！】王雪","id":"130790","name":"得意のセールストーク！","num":1,"rarity":3},{"actor":"連尺野初魅","actorRomanization":"Renjakuno Hatsumi","attribute":"彩属性","fullName":"【助手席、空いているぞ】連尺野初魅","id":"130800","name":"助手席、空いているぞ","num":1,"rarity":3},{"actor":"リリヤ・クルトベイ","actorRomanization":"Lilja Kurtbay","attribute":"凛属性","fullName":"【穏やかな昼下がり】リリヤ・クルトベイ","id":"130810","name":"穏やかな昼下がり","num":1,"rarity":3},{"actor":"本巣叶羽","actorRomanization":"Motosu Towa","attribute":"陽属性","fullName":"【最前列の景色】本巣叶羽","id":"130820","name":"最前列の景色","num":1,"rarity":3},{"actor":"静香","actorRomanization":" Shizuka","attribute":"彩属性","fullName":"【無邪気な称賛】静香","id":"130830","name":"無邪気な称賛","num":1,"rarity":3},{"actor":"猫足蕾","actorRomanization":"Nekoashi Tsubomi","attribute":"凛属性","fullName":"【数式はここに当てはめて……】猫足蕾","id":"130840","name":"数式はここに当てはめて……","num":1,"rarity":3},{"actor":"カトリナ・グリーベル","actorRomanization":"Kathrina Griebel","attribute":"陽属性","fullName":"【髪を撫でられ……】カトリナ・グリーベル","id":"130850","name":"髪を撫でられ……","num":1,"rarity":3},{"actor":"与那国緋花里","actorRomanization":"Yonaguni Hikari","attribute":"憐属性","fullName":"【気分はプロフェッショナル！】与那国緋花里","id":"130860","name":"気分はプロフェッショナル！","num":1,"rarity":3},{"actor":"鳳ここな","actorRomanization":"Otori Kokona","attribute":"彩属性","fullName":"【変わるあの子を見て】鳳ここな","id":"130870","name":"変わるあの子を見て","num":1,"rarity":3},{"actor":"筆島しぐれ","actorRomanization":"Fudeshima Shigure","attribute":"陽属性","fullName":"【ピースメーカーは追い求める】筆島しぐれ","id":"130880","name":"ピースメーカーは追い求める","num":1,"rarity":3},{"actor":"千寿暦","actorRomanization":"Senju Koyomi","attribute":"憐属性","fullName":"【料理も一流……？】千寿暦","id":"130890","name":"料理も一流……？","num":1,"rarity":3},{"actor":"烏森大黒","actorRomanization":"Karasumori Daikoku","attribute":"凛属性","fullName":"【主の過去を知り……】烏森大黒","id":"130900","name":"主の過去を知り……","num":1,"rarity":3},{"actor":"リリヤ・クルトベイ","actorRomanization":"Lilja Kurtbay","attribute":"陽属性","fullName":"【空想式場】リリヤ・クルトベイ","id":"130910","name":"空想式場","num":1,"rarity":3},{"actor":"鳳ここな","actorRomanization":"Otori Kokona","attribute":"彩属性","fullName":"【悲哀と恋慕の旋律】鳳ここな","id":"140010","name":"悲哀と恋慕の旋律","num":2,"rarity":4},{"actor":"新妻八恵","actorRomanization":"Niizuma Yae","attribute":"憐属性","fullName":"【大切で大好きな劇団】新妻八恵","id":"140020","name":"大切で大好きな劇団","num":2,"rarity":4},{"actor":"柳場ぱんだ","actorRomanization":"Yanagiba Panda","attribute":"陽属性","fullName":"【あなたをお待ちしておりました】柳場ぱんだ","id":"140030","name":"あなたをお待ちしておりました","num":2,"rarity":4},{"actor":"流石知冴","actorRomanization":"Sasuga Chisa","attribute":"陽属性","fullName":"【君を求めていた】流石知冴","id":"140040","name":"君を求めていた","num":2,"rarity":4},{"actor":"舎人仁花子","actorRomanization":"Toneri Nikako","attribute":"憐属性","fullName":"【純真無垢な笑顔】舎人仁花子","id":"140050","name":"純真無垢な笑顔","num":2,"rarity":4},{"actor":"萬容","actorRomanization":"Yorozu Iruru","attribute":"凛属性","fullName":"【満たされない心】萬容","id":"140060","name":"満たされない心","num":2,"rarity":4},{"actor":"筆島しぐれ","actorRomanization":"Fudeshima Shigure","attribute":"彩属性","fullName":"【吸血しちゃうぞっ♪】筆島しぐれ","id":"140070","name":"吸血しちゃうぞっ♪","num":2,"rarity":4},{"actor":"千寿暦","actorRomanization":"Senju Koyomi","attribute":"凛属性","fullName":"【幼き日の情景】千寿暦","id":"140080","name":"幼き日の情景","num":2,"rarity":4},{"actor":"ラモーナ・ウォルフ","actorRomanization":"Ramona Wolf","attribute":"陽属性","fullName":"【かつての友との別れ】ラモーナ・ウォルフ","id":"140090","name":"かつての友との別れ","num":2,"rarity":4},{"actor":"リリヤ・クルトベイ","actorRomanization":"Lilja Kurtbay","attribute":"憐属性","fullName":"【オーロラの精霊】リリヤ・クルトベイ","id":"140100","name":"オーロラの精霊","num":2,"rarity":4},{"actor":"千寿いろは","actorRomanization":"Senju Iroha","attribute":"陽属性","fullName":"【私を見守る大切な蝶】千寿いろは","id":"140110","name":"私を見守る大切な蝶","num":2,"rarity":4},{"actor":"白丸美兎","actorRomanization":"Shiromaru Mito","attribute":"彩属性","fullName":"【世界が色づくその瞬間】白丸美兎","id":"140120","name":"世界が色づくその瞬間","num":2,"rarity":4},{"actor":"本巣叶羽","actorRomanization":"Motosu Towa","attribute":"凛属性","fullName":"【月下の神秘】本巣叶羽","id":"140130","name":"月下の神秘","num":2,"rarity":4},{"actor":"カトリナ・グリーベル","actorRomanization":"Kathrina Griebel","attribute":"陽属性","fullName":"【憧れに思いを馳せて】カトリナ・グリーベル","id":"140140","name":"憧れに思いを馳せて","num":2,"rarity":4},{"actor":"烏森大黒","actorRomanization":"Karasumori Daikoku","attribute":"憐属性","fullName":"【狂気の果ての虚無】烏森大黒","id":"140150","name":"狂気の果ての虚無","num":2,"rarity":4},{"actor":"連尺野初魅","actorRomanization":"Renjakuno Hatsumi","attribute":"憐属性","fullName":"【悪意に満ちた観察者】連尺野初魅","id":"140160","name":"悪意に満ちた観察者","num":2,"rarity":4},{"actor":"猫足蕾","actorRomanization":"Nekoashi Tsubomi","attribute":"凛属性","fullName":"【追想の帰路】猫足蕾","id":"140170","name":"追想の帰路","num":2,"rarity":4},{"actor":"阿岐留カミラ","actorRomanization":"Akiru Kamira","attribute":"凛属性","fullName":"【茜海に満たされて】阿岐留カミラ","id":"140180","name":"茜海に満たされて","num":2,"rarity":4},{"actor":"新妻八恵","actorRomanization":"Niizuma Yae","attribute":"凛属性","fullName":"【お口に合いますように♪】新妻八恵","id":"140190","name":"お口に合いますように♪","num":2,"rarity":4},{"actor":"静香","actorRomanization":" Shizuka","attribute":"凛属性","fullName":"【マジカル☆スイーツ】静香","id":"140200","name":"マジカル☆スイーツ","num":2,"rarity":4},{"actor":"王雪","actorRomanization":"Wang Xue","attribute":"彩属性","fullName":"【夜市の王】王雪","id":"140210","name":"夜市の王","num":2,"rarity":4},{"actor":"リリヤ・クルトベイ","actorRomanization":"Lilja Kurtbay","attribute":"彩属性","fullName":"【妖艶に誘われて】リリヤ・クルトベイ","id":"140220","name":"妖艶に誘われて","num":2,"rarity":4},{"actor":"白丸美兎","actorRomanization":"Shiromaru Mito","attribute":"憐属性","fullName":"【光さす世界に】白丸美兎","id":"140240","name":"光さす世界に","num":2,"rarity":4},{"actor":"千寿いろは","actorRomanization":"Senju Iroha","attribute":"憐属性","fullName":"【移りゆく世界の中で】千寿いろは","id":"140250","name":"移りゆく世界の中で","num":2,"rarity":4},{"actor":"舎人仁花子","actorRomanization":"Toneri Nikako","attribute":"彩属性","fullName":"【アオハル応援団長】舎人仁花子","id":"140260","name":"アオハル応援団長","num":2,"rarity":4},{"actor":"カトリナ・グリーベル","actorRomanization":"Kathrina Griebel","attribute":"彩属性","fullName":"【Pretty Cheer Girl】カトリナ・グリーベル","id":"140270","name":"Pretty Cheer Girl","num":2,"rarity":4},{"actor":"千寿暦","actorRomanization":"Senju Koyomi","attribute":"陽属性","fullName":"【月光が映し出す罪と後悔】千寿暦","id":"140280","name":"月光が映し出す罪と後悔","num":2,"rarity":4},{"actor":"連尺野初魅","actorRomanization":"Renjakuno Hatsumi","attribute":"陽属性","fullName":"【甘美なる悪逆へ誘おう】連尺野初魅","id":"140290","name":"甘美なる悪逆へ誘おう","num":2,"rarity":4},{"actor":"柳場ぱんだ","actorRomanization":"Yanagiba Panda","attribute":"凛属性","fullName":"【綾錦の月影】柳場ぱんだ","id":"140300","name":"綾錦の月影","num":2,"rarity":4},{"actor":"与那国緋花里","actorRomanization":"Yonaguni Hikari","attribute":"凛属性","fullName":"【妖刀の一薙ぎ】与那国緋花里","id":"140310","name":"妖刀の一薙ぎ","num":2,"rarity":4},{"actor":"王雪","actorRomanization":"Wang Xue","attribute":"憐属性","fullName":"【南十字を目指して】王雪","id":"140320","name":"南十字を目指して","num":2,"rarity":4},{"actor":"千寿暦","actorRomanization":"Senju Koyomi","attribute":"憐属性","fullName":"【コル・スコルピイ】千寿暦","id":"140330","name":"コル・スコルピイ","num":2,"rarity":4},{"actor":"鳳ここな","actorRomanization":"Otori Kokona","attribute":"憐属性","fullName":"【ステキな物語はいかがですか？】鳳ここな","id":"140340","name":"ステキな物語はいかがですか？","num":2,"rarity":4},{"actor":"流石知冴","actorRomanization":"Sasuga Chisa","attribute":"憐属性","fullName":"【おとぎの国の食事会】流石知冴","id":"140350","name":"おとぎの国の食事会","num":2,"rarity":4},{"actor":"千寿いろは","actorRomanization":"Senju Iroha","attribute":"彩属性","fullName":"【真の力を見せる時！】千寿いろは","id":"140360","name":"真の力を見せる時！","num":2,"rarity":4},{"actor":"猫足蕾","actorRomanization":"Nekoashi Tsubomi","attribute":"彩属性","fullName":"【戦い続ける魔法少女】猫足蕾","id":"140370","name":"戦い続ける魔法少女","num":2,"rarity":4},{"actor":"ラモーナ・ウォルフ","actorRomanization":"Ramona Wolf","attribute":"凛属性","fullName":"【名探偵の悲哀】ラモーナ・ウォルフ","id":"140380","name":"名探偵の悲哀","num":2,"rarity":4},{"actor":"王雪","actorRomanization":"Wang Xue","attribute":"凛属性","fullName":"【本当のギムレット】王雪","id":"140390","name":"本当のギムレット","num":2,"rarity":4},{"actor":"本巣叶羽","actorRomanization":"Motosu Towa","attribute":"陽属性","fullName":"【夕暮れ時には甘えてみて】本巣叶羽","id":"140400","name":"夕暮れ時には甘えてみて","num":2,"rarity":4},{"actor":"筆島しぐれ","actorRomanization":"Fudeshima Shigure","attribute":"陽属性","fullName":"【巡り合わせの落葉】筆島しぐれ","id":"140410","name":"巡り合わせの落葉","num":2,"rarity":4},{"actor":"萬容","actorRomanization":"Yorozu Iruru","attribute":"彩属性","fullName":"【囚われてなお渇望するもの】萬容","id":"140420","name":"囚われてなお渇望するもの","num":2,"rarity":4},{"actor":"烏森大黒","actorRomanization":"Karasumori Daikoku","attribute":"彩属性","fullName":"【縛めを解いてくれた人と共に】烏森大黒","id":"140430","name":"縛めを解いてくれた人と共に","num":2,"rarity":4},{"actor":"静香","actorRomanization":" Shizuka","attribute":"陽属性","fullName":"【その手を取り、翼並べて】静香","id":"140440","name":"その手を取り、翼並べて","num":2,"rarity":4},{"actor":"鳳ここな","actorRomanization":"Otori Kokona","attribute":"陽属性","fullName":"【片割れを見つけた鳥】鳳ここな","id":"140450","name":"片割れを見つけた鳥","num":2,"rarity":4},{"actor":"与那国緋花里","actorRomanization":"Yonaguni Hikari","attribute":"憐属性","fullName":"【遠い遠い雪催い】与那国緋花里","id":"140460","name":"遠い遠い雪催い","num":2,"rarity":4},{"actor":"阿岐留カミラ","actorRomanization":"Akiru Kamira","attribute":"憐属性","fullName":"【銀世界に冴ゆる心友】阿岐留カミラ","id":"140470","name":"銀世界に冴ゆる心友","num":2,"rarity":4},{"actor":"リリヤ・クルトベイ","actorRomanization":"Lilja Kurtbay","attribute":"陽属性","fullName":"【CEOからの特別な……♡】リリヤ・クルトベイ","id":"140480","name":"CEOからの特別な……♡","num":2,"rarity":4},{"actor":"王雪","actorRomanization":"Wang Xue","attribute":"陽属性","fullName":"【あなたにだけのプレゼント】王雪","id":"140490","name":"あなたにだけのプレゼント","num":2,"rarity":4},{"actor":"カトリナ・グリーベル","actorRomanization":"Kathrina Griebel","attribute":"憐属性","fullName":"【瑞祥新春の舞】カトリナ・グリーベル","id":"140500","name":"瑞祥新春の舞","num":2,"rarity":4},{"actor":"ラモーナ・ウォルフ","actorRomanization":"Ramona Wolf","attribute":"憐属性","fullName":"【人里の宴も悪くない】ラモーナ・ウォルフ","id":"140510","name":"人里の宴も悪くない","num":2,"rarity":4},{"actor":"本巣叶羽","actorRomanization":"Motosu Towa","attribute":"彩属性","fullName":"【Electric Wonderland】本巣叶羽","id":"140520","name":"Electric Wonderland","num":2,"rarity":4},{"actor":"千寿いろは","actorRomanization":"Senju Iroha","attribute":"凛属性","fullName":"【Electric Tea Party】千寿いろは","id":"140530","name":"Electric Tea Party","num":2,"rarity":4},{"actor":"筆島しぐれ","actorRomanization":"Fudeshima Shigure","attribute":"凛属性","fullName":"【悩める迷宮での出会い】筆島しぐれ","id":"140540","name":"悩める迷宮での出会い","num":2,"rarity":4},{"actor":"舎人仁花子","actorRomanization":"Toneri Nikako","attribute":"凛属性","fullName":"【導きの燐光】舎人仁花子","id":"140550","name":"導きの燐光","num":2,"rarity":4},{"actor":"流石知冴","actorRomanization":"Sasuga Chisa","attribute":"彩属性","fullName":"【ナイト・オブ・ビビッド】流石知冴","id":"140560","name":"ナイト・オブ・ビビッド","num":2,"rarity":4},{"actor":"柳場ぱんだ","actorRomanization":"Yanagiba Panda","attribute":"彩属性","fullName":"【マジカルポップウィッチ】柳場ぱんだ","id":"140570","name":"マジカルポップウィッチ","num":2,"rarity":4},{"actor":"連尺野初魅","actorRomanization":"Renjakuno Hatsumi","attribute":"凛属性","fullName":"【ひと口で落ちる甘やかな酔い】連尺野初魅","id":"140600","name":"ひと口で落ちる甘やかな酔い","num":2,"rarity":4},{"actor":"萬容","actorRomanization":"Yorozu Iruru","attribute":"凛属性","fullName":"【求め焦がれる危険な味わい】萬容","id":"140610","name":"求め焦がれる危険な味わい","num":2,"rarity":4},{"actor":"猫足蕾","actorRomanization":"Nekoashi Tsubomi","attribute":"陽属性","fullName":"【華は海底に眠る】猫足蕾","id":"140620","name":"華は海底に眠る","num":2,"rarity":4},{"actor":"千寿いろは","actorRomanization":"Senju Iroha","attribute":"陽属性","fullName":"【水海に月は満ち】千寿いろは","id":"140630","name":"水海に月は満ち","num":2,"rarity":4},{"actor":"新妻八恵","actorRomanization":"Niizuma Yae","attribute":"凛属性","fullName":"【いちばんたいせつなことは】新妻八恵","id":"140660","name":"いちばんたいせつなことは","num":2,"rarity":4},{"actor":"鳳ここな","actorRomanization":"Otori Kokona","attribute":"凛属性","fullName":"【夜空を見れば、思い出す】鳳ここな","id":"140670","name":"夜空を見れば、思い出す","num":2,"rarity":4},{"actor":"烏森大黒","actorRomanization":"Karasumori Daikoku","attribute":"憐属性","fullName":"【カオティックキュート】烏森大黒","id":"140680","name":"カオティックキュート","num":2,"rarity":4},{"actor":"筆島しぐれ","actorRomanization":"Fudeshima Shigure","attribute":"憐属性","fullName":"【サイバーガーディアン】筆島しぐれ","id":"140690","name":"サイバーガーディアン","num":2,"rarity":4},{"actor":"白丸美兎","actorRomanization":"Shiromaru Mito","attribute":"彩属性","fullName":"【武の頂を目指して】白丸美兎","id":"140700","name":"武の頂を目指して","num":2,"rarity":4},{"actor":"与那国緋花里","actorRomanization":"Yonaguni Hikari","attribute":"彩属性","fullName":"【決闘者は仙人の如く】与那国緋花里","id":"140710","name":"決闘者は仙人の如く","num":2,"rarity":4},{"actor":"鳳ここな","actorRomanization":"Otori Kokona","attribute":"憐属性","fullName":"【絵本から飛び出せば】鳳ここな","id":"140720","name":"絵本から飛び出せば","num":2,"rarity":4},{"actor":"柳場ぱんだ","actorRomanization":"Yanagiba Panda","attribute":"憐属性","fullName":"【思い出のカルテリーノ】柳場ぱんだ","id":"140730","name":"思い出のカルテリーノ","num":2,"rarity":4},{"actor":"千寿暦","actorRomanization":"Senju Koyomi","attribute":"彩属性","fullName":"【舞踏会は波乱と恋の予感？！】千寿暦","id":"140740","name":"舞踏会は波乱と恋の予感？！","num":2,"rarity":4},{"actor":"ラモーナ・ウォルフ","actorRomanization":"Ramona Wolf","attribute":"彩属性","fullName":"【冷酷な辺境伯に求婚されてます】ラモーナ・ウォルフ","id":"140750","name":"冷酷な辺境伯に求婚されてます","num":2,"rarity":4},{"actor":"萬容","actorRomanization":"Yorozu Iruru","attribute":"陽属性","fullName":"【初めての恋は成就したか】萬容","id":"140760","name":"初めての恋は成就したか","num":2,"rarity":4},{"actor":"舎人仁花子","actorRomanization":"Toneri Nikako","attribute":"陽属性","fullName":"【正しくあるべき人の道を説く】舎人仁花子","id":"140770","name":"正しくあるべき人の道を説く","num":2,"rarity":4},{"actor":"阿岐留カミラ","actorRomanization":"Akiru Kamira","attribute":"彩属性","fullName":"【LIVE YOUR STYLE】阿岐留カミラ","id":"140780","name":"LIVE YOUR STYLE","num":2,"rarity":4},{"actor":"リリヤ・クルトベイ","actorRomanization":"Lilja Kurtbay","attribute":"彩属性","fullName":"【私だけの美学】リリヤ・クルトベイ","id":"140790","name":"私だけの美学","num":2,"rarity":4},{"actor":"静香","actorRomanization":" Shizuka","attribute":"凛属性","fullName":"【オートマタのテアトルにて】静香","id":"140800","name":"オートマタのテアトルにて","num":2,"rarity":4},{"actor":"カトリナ・グリーベル","actorRomanization":"Kathrina Griebel","attribute":"凛属性","fullName":"【心躍る人形劇の裏】カトリナ・グリーベル","id":"140810","name":"心躍る人形劇の裏","num":2,"rarity":4},{"actor":"柳場ぱんだ","actorRomanization":"Yanagiba Panda","attribute":"彩属性","fullName":"【がおー！のレッスン】柳場ぱんだ","id":"140820","name":"がおー！のレッスン","num":2,"rarity":4},{"actor":"新妻八恵","actorRomanization":"Niizuma Yae","attribute":"彩属性","fullName":"【ペンギン・ア・ゴーゴー！】新妻八恵","id":"140830","name":"ペンギン・ア・ゴーゴー！","num":2,"rarity":4},{"actor":"与那国緋花里","actorRomanization":"Yonaguni Hikari","attribute":"陽属性","fullName":"【雨上がりには特大スクープ！】与那国緋花里","id":"140840","name":"雨上がりには特大スクープ！","num":2,"rarity":4},{"actor":"王雪","actorRomanization":"Wang Xue","attribute":"陽属性","fullName":"【雨上がりの君を待って】王雪","id":"140850","name":"雨上がりの君を待って","num":2,"rarity":4},{"actor":"本巣叶羽","actorRomanization":"Motosu Towa","attribute":"憐属性","fullName":"【連なる薔薇の懐かしき香り】本巣叶羽","id":"140860","name":"連なる薔薇の懐かしき香り","num":2,"rarity":4},{"actor":"白丸美兎","actorRomanization":"Shiromaru Mito","attribute":"憐属性","fullName":"【白き死神は戦場を駆け】白丸美兎","id":"140870","name":"白き死神は戦場を駆け","num":2,"rarity":4},{"actor":"阿岐留カミラ","actorRomanization":"Akiru Kamira","attribute":"陽属性","fullName":"【春の紫苑も良いでしょう？】阿岐留カミラ","id":"140880","name":"春の紫苑も良いでしょう？","num":2,"rarity":4},{"actor":"白丸美兎","actorRomanization":"Shiromaru Mito","attribute":"陽属性","fullName":"【朱の菜花は春を告げ】白丸美兎","id":"140890","name":"朱の菜花は春を告げ","num":2,"rarity":4},{"actor":"リリヤ・クルトベイ","actorRomanization":"Lilja Kurtbay","attribute":"凛属性","fullName":"【江楓にお覚悟を】リリヤ・クルトベイ","id":"140900","name":"江楓にお覚悟を","num":2,"rarity":4},{"actor":"本巣叶羽","actorRomanization":"Motosu Towa","attribute":"凛属性","fullName":"【天才の有る栖にようこそ】本巣叶羽","id":"140910","name":"天才の有る栖にようこそ","num":2,"rarity":4},{"actor":"烏森大黒","actorRomanization":"Karasumori Daikoku","attribute":"陽属性","fullName":"【平和で幸せな悪魔憑き】烏森大黒","id":"140920","name":"平和で幸せな悪魔憑き","num":2,"rarity":4},{"actor":"連尺野初魅","actorRomanization":"Renjakuno Hatsumi","attribute":"彩属性","fullName":"【銀弾は正鵠の射手】連尺野初魅","id":"140930","name":"銀弾は正鵠の射手","num":2,"rarity":4},{"actor":"舎人仁花子","actorRomanization":"Toneri Nikako","attribute":"憐属性","fullName":"【プレイス・ユア・ベット】舎人仁花子","id":"140940","name":"プレイス・ユア・ベット","num":2,"rarity":4},{"actor":"萬容","actorRomanization":"Yorozu Iruru","attribute":"憐属性","fullName":"【オール・オア・ナッシング】萬容","id":"140950","name":"オール・オア・ナッシング","num":2,"rarity":4},{"actor":"千寿いろは","actorRomanization":"Senju Iroha","attribute":"凛属性","fullName":"【旅路は銀の靴とともに】千寿いろは","id":"140960","name":"旅路は銀の靴とともに","num":2,"rarity":4},{"actor":"千寿暦","actorRomanization":"Senju Koyomi","attribute":"凛属性","fullName":"【小さなあの子を待ちながら】千寿暦","id":"140970","name":"小さなあの子を待ちながら","num":2,"rarity":4},{"actor":"静香","actorRomanization":" Shizuka","attribute":"憐属性","fullName":"【とある悪魔の幸福】静香","id":"140980","name":"とある悪魔の幸福","num":2,"rarity":4},{"actor":"鳳ここな","actorRomanization":"Otori Kokona","attribute":"彩属性","fullName":"【あなたの声は潮騒に】鳳ここな","id":"140990","name":"あなたの声は潮騒に","num":2,"rarity":4},{"actor":"筆島しぐれ","actorRomanization":"Fudeshima Shigure","attribute":"彩属性","fullName":"【メイク・サム・ノイズ！】筆島しぐれ","id":"141000","name":"メイク・サム・ノイズ！","num":2,"rarity":4},{"actor":"連尺野初魅","actorRomanization":"Renjakuno Hatsumi","attribute":"彩属性","fullName":"【ミッドナイト・グルーヴ】連尺野初魅","id":"141010","name":"ミッドナイト・グルーヴ","num":2,"rarity":4},{"actor":"舎人仁花子","actorRomanization":"Toneri Nikako","attribute":"凛属性","fullName":"【スカイブルーにも届くかも】舎人仁花子","id":"141020","name":"スカイブルーにも届くかも","num":2,"rarity":4},{"actor":"烏森大黒","actorRomanization":"Karasumori Daikoku","attribute":"凛属性","fullName":"【マリンブルーも涼やかに】烏森大黒","id":"141030","name":"マリンブルーも涼やかに","num":2,"rarity":4},{"actor":"流石知冴","actorRomanization":"Sasuga Chisa","attribute":"陽属性","fullName":"【一夜、自由の翼になるよ】流石知冴","id":"141040","name":"一夜、自由の翼になるよ","num":2,"rarity":4},{"actor":"新妻八恵","actorRomanization":"Niizuma Yae","attribute":"陽属性","fullName":"【今宵、空灯篭のように】新妻八恵","id":"141050","name":"今宵、空灯篭のように","num":2,"rarity":4},{"actor":"ラモーナ・ウォルフ","actorRomanization":"Ramona Wolf","attribute":"陽属性","fullName":"【憂い、門出、晴れなくて】ラモーナ・ウォルフ","id":"141060","name":"憂い、門出、晴れなくて","num":2,"rarity":4},{"actor":"与那国緋花里","actorRomanization":"Yonaguni Hikari","attribute":"陽属性","fullName":"【歌い、踊り、乾杯を】与那国緋花里","id":"141070","name":"歌い、踊り、乾杯を","num":2,"rarity":4},{"actor":"猫足蕾","actorRomanization":"Nekoashi Tsubomi","attribute":"憐属性","fullName":"【デンキウィズザ……！？】猫足蕾","id":"141080","name":"デンキウィズザ……！？","num":2,"rarity":4},{"actor":"本巣叶羽","actorRomanization":"Motosu Towa","attribute":"憐属性","fullName":"【デンキインザムーーーーーン】本巣叶羽","id":"141090","name":"デンキインザムーーーーーン","num":2,"rarity":4},{"actor":"王雪","actorRomanization":"Wang Xue","attribute":"彩属性","fullName":"【リクエストはロックナンバーで】王雪","id":"141100","name":"リクエストはロックナンバーで","num":2,"rarity":4},{"actor":"千寿暦","actorRomanization":"Senju Koyomi","attribute":"彩属性","fullName":"【玉椿、夜水に灯り】千寿暦","id":"141110","name":"玉椿、夜水に灯り","num":2,"rarity":4},{"actor":"カトリナ・グリーベル","actorRomanization":"Kathrina Griebel","attribute":"凛属性","fullName":"【秘密のおしゃべり】カトリナ・グリーベル","id":"141120","name":"秘密のおしゃべり","num":2,"rarity":4},{"actor":"流石知冴","actorRomanization":"Sasuga Chisa","attribute":"凛属性","fullName":"【過ぎた時を悔いても】流石知冴","id":"141130","name":"過ぎた時を悔いても","num":2,"rarity":4},{"actor":"千寿暦","actorRomanization":"Senju Koyomi","attribute":"憐属性","fullName":"【行き先は星々のもと】千寿暦","id":"141140","name":"行き先は星々のもと","num":2,"rarity":4},{"actor":"王雪","actorRomanization":"Wang Xue","attribute":"憐属性","fullName":"【旅情の旨味】王雪","id":"141150","name":"旅情の旨味","num":2,"rarity":4},{"actor":"連尺野初魅","actorRomanization":"Renjakuno Hatsumi","attribute":"憐属性","fullName":"【硝煙くゆるコールド・シティ】連尺野初魅","id":"141160","name":"硝煙くゆるコールド・シティ","num":2,"rarity":4},{"actor":"烏森大黒","actorRomanization":"Karasumori Daikoku","attribute":"憐属性","fullName":"【45口径と少女のフィルム】烏森大黒","id":"141170","name":"45口径と少女のフィルム","num":2,"rarity":4},{"actor":"リリヤ・クルトベイ","actorRomanization":"Lilja Kurtbay","attribute":"憐属性","fullName":"【Here's the smell of】リリヤ・クルトベイ","id":"141180","name":"Here's the smell of","num":2,"rarity":4},{"actor":"ラモーナ・ウォルフ","actorRomanization":"Ramona Wolf","attribute":"憐属性","fullName":"【Our fears in】ラモーナ・ウォルフ","id":"141190","name":"Our fears in","num":2,"rarity":4},{"actor":"阿岐留カミラ","actorRomanization":"Akiru Kamira","attribute":"凛属性","fullName":"【SWEEP U OFF Ur ♡！】阿岐留カミラ","id":"141200","name":"SWEEP U OFF Ur ♡！","num":2,"rarity":4},{"actor":"与那国緋花里","actorRomanization":"Yonaguni Hikari","attribute":"凛属性","fullName":"【HANG IN THERE!】与那国緋花里","id":"141210","name":"HANG IN THERE!","num":2,"rarity":4},{"actor":"新妻八恵","actorRomanization":"Niizuma Yae","attribute":"彩属性","fullName":"【旅するみるくティーン】新妻八恵","id":"141220","name":"旅するみるくティーン","num":2,"rarity":4},{"actor":"静香","actorRomanization":" Shizuka","attribute":"彩属性","fullName":"【ソルト・フラグメント】静香","id":"141230","name":"ソルト・フラグメント","num":2,"rarity":4},{"actor":"高海千歌","actorRomanization":"Takami Chika","attribute":"陽属性","fullName":"【千の歌を紡ぐ幻影】高海千歌","id":"141240","name":"千の歌を紡ぐ幻影","num":2,"rarity":4},{"actor":"桜内梨子","actorRomanization":"Sakurauchi Riko","attribute":"彩属性","fullName":"【空を知り、恋をして】桜内梨子","id":"141250","name":"空を知り、恋をして","num":2,"rarity":4},{"actor":"黒澤ダイヤ","actorRomanization":"Kurosawa Dia","attribute":"憐属性","fullName":"【diadem for silver bullet】黒澤ダイヤ","id":"141260","name":"diadem for silver bullet","num":2,"rarity":4},{"actor":"黒澤ルビィ","actorRomanization":"Kurosawa Ruby","attribute":"陽属性","fullName":"【夜空をかけるビジョナリィ】黒澤ルビィ","id":"141270","name":"夜空をかけるビジョナリィ","num":2,"rarity":4},{"actor":"津島善子","actorRomanization":"Tsushima Yoshiko","attribute":"凛属性","fullName":"【ようこそ不思議なこの国へ】津島善子","id":"141280","name":"ようこそ不思議なこの国へ","num":2,"rarity":4},{"actor":"鳳ここな","actorRomanization":"Otori Kokona","attribute":"憐属性","fullName":"【光の海でも輝いて】鳳ここな","id":"141290","name":"光の海でも輝いて","num":2,"rarity":4},{"actor":"千寿いろは","actorRomanization":"Senju Iroha","attribute":"彩属性","fullName":"【LIVE with SUNSHINE!!】千寿いろは","id":"141300","name":"LIVE with SUNSHINE!!","num":2,"rarity":4},{"actor":"筆島しぐれ","actorRomanization":"Fudeshima Shigure","attribute":"陽属性","fullName":"【ひんやり、きらきら】筆島しぐれ","id":"141310","name":"ひんやり、きらきら","num":2,"rarity":4},{"actor":"連尺野初魅","actorRomanization":"Renjakuno Hatsumi","attribute":"陽属性","fullName":"【楽園の主はいたずら中】連尺野初魅","id":"141320","name":"楽園の主はいたずら中","num":2,"rarity":4},{"actor":"静香","actorRomanization":" Shizuka","attribute":"凛属性","fullName":"【エリートサンタは夜を駆け】静香","id":"141330","name":"エリートサンタは夜を駆け","num":2,"rarity":4},{"actor":"鳳ここな","actorRomanization":"Otori Kokona","attribute":"凛属性","fullName":"【新人サンタはあわてんぼう】鳳ここな","id":"141340","name":"新人サンタはあわてんぼう","num":2,"rarity":4},{"actor":"猫足蕾","actorRomanization":"Nekoashi Tsubomi","attribute":"彩属性","fullName":"【慶賀へ至る富正月】猫足蕾","id":"141350","name":"慶賀へ至る富正月","num":2,"rarity":4},{"actor":"烏森大黒","actorRomanization":"Karasumori Daikoku","attribute":"彩属性","fullName":"【金花ほころぶ祝言のとき】烏森大黒","id":"141360","name":"金花ほころぶ祝言のとき","num":2,"rarity":4},{"actor":"カトリナ・グリーベル","actorRomanization":"Kathrina Griebel","attribute":"憐属性","fullName":"【アクアアルタでつかまえて】カトリナ・グリーベル","id":"141370","name":"アクアアルタでつかまえて","num":2,"rarity":4},{"actor":"新妻八恵","actorRomanization":"Niizuma Yae","attribute":"憐属性","fullName":"【いざ、仮面舞踏会へ！】新妻八恵","id":"141380","name":"いざ、仮面舞踏会へ！","num":2,"rarity":4},{"actor":"ラモーナ・ウォルフ","actorRomanization":"Ramona Wolf","attribute":"陽属性","fullName":"【挑まれた勝負に思い巡らせ】ラモーナ・ウォルフ","id":"141390","name":"挑まれた勝負に思い巡らせ","num":2,"rarity":4},{"actor":"リリヤ・クルトベイ","actorRomanization":"Lilja Kurtbay","attribute":"陽属性","fullName":"【その心、今夜頂きに参ります】リリヤ・クルトベイ","id":"141400","name":"その心、今夜頂きに参ります","num":2,"rarity":4},{"actor":"阿岐留カミラ","actorRomanization":"Akiru Kamira","attribute":"凛属性","fullName":"【いたずら妖精がご招待】阿岐留カミラ","id":"141410","name":"いたずら妖精がご招待","num":2,"rarity":4},{"actor":"白丸美兎","actorRomanization":"Shiromaru Mito","attribute":"凛属性","fullName":"【それでも止まらぬ恋心】白丸美兎","id":"141420","name":"それでも止まらぬ恋心","num":2,"rarity":4},{"actor":"柳場ぱんだ","actorRomanization":"Yanagiba Panda","attribute":"憐属性","fullName":"【星のようにまぶしい出会い】柳場ぱんだ","id":"141430","name":"星のようにまぶしい出会い","num":2,"rarity":4},{"actor":"流石知冴","actorRomanization":"Sasuga Chisa","attribute":"憐属性","fullName":"【大事なのは信じることさ！】流石知冴","id":"141440","name":"大事なのは信じることさ！","num":2,"rarity":4},{"actor":"千寿暦","actorRomanization":"Senju Koyomi","attribute":"陽属性","fullName":"【スウィート・セレクション】千寿暦","id":"141450","name":"スウィート・セレクション","num":2,"rarity":4},{"actor":"与那国緋花里","actorRomanization":"Yonaguni Hikari","attribute":"陽属性","fullName":"【ハートフル・ショッピング】与那国緋花里","id":"141460","name":"ハートフル・ショッピング","num":2,"rarity":4},{"actor":"萬容","actorRomanization":"Yorozu Iruru","attribute":"彩属性","fullName":"【一緒にツーリング！】萬容","id":"141470","name":"一緒にツーリング！","num":2,"rarity":4},{"actor":"舎人仁花子","actorRomanization":"Toneri Nikako","attribute":"彩属性","fullName":"【空飛ぶテントで】舎人仁花子","id":"141480","name":"空飛ぶテントで","num":2,"rarity":4},{"actor":"与那国緋花里","actorRomanization":"Yonaguni Hikari","attribute":"凛属性","fullName":"【コンクリート・ジャム】与那国緋花里","id":"141490","name":"コンクリート・ジャム","num":2,"rarity":4},{"actor":"王雪","actorRomanization":"Wang Xue","attribute":"凛属性","fullName":"【ストリート・スクリプト】王雪","id":"141500","name":"ストリート・スクリプト","num":2,"rarity":4},{"actor":"猫足蕾","actorRomanization":"Nekoashi Tsubomi","attribute":"陽属性","fullName":"【春めく花園を切り取って】猫足蕾","id":"141510","name":"春めく花園を切り取って","num":2,"rarity":4},{"actor":"阿岐留カミラ","actorRomanization":"Akiru Kamira","attribute":"陽属性","fullName":"【昼下がりのPhoto Spring】阿岐留カミラ","id":"141520","name":"昼下がりのPhoto Spring","num":2,"rarity":4},{"actor":"鳳ここな","actorRomanization":"Otori Kokona","attribute":"彩属性","fullName":"【夜、静かなミュージアムで】鳳ここな","id":"141530","name":"夜、静かなミュージアムで","num":2,"rarity":4},{"actor":"流石知冴","actorRomanization":"Sasuga Chisa","attribute":"彩属性","fullName":"【密やかに微笑む美の肖像】流石知冴","id":"141540","name":"密やかに微笑む美の肖像","num":2,"rarity":4},{"actor":"白丸美兎","actorRomanization":"Shiromaru Mito","attribute":"凛属性","fullName":"【霹靂は夜雨を駆け】白丸美兎","id":"141550","name":"霹靂は夜雨を駆け","num":2,"rarity":4},{"actor":"本巣叶羽","actorRomanization":"Motosu Towa","attribute":"凛属性","fullName":"【アンタには一発で充分】本巣叶羽","id":"141560","name":"アンタには一発で充分","num":2,"rarity":4},{"actor":"鳳ここな","actorRomanization":"Otori Kokona","attribute":"陽属性","fullName":"【ホエールウォッチング！】鳳ここな","id":"141570","name":"ホエールウォッチング！","num":2,"rarity":4},{"actor":"リリヤ・クルトベイ","actorRomanization":"Lilja Kurtbay","attribute":"陽属性","fullName":"【異邦の湯に足を浸して】リリヤ・クルトベイ","id":"141580","name":"異邦の湯に足を浸して","num":2,"rarity":4},{"actor":"千寿暦","actorRomanization":"Senju Koyomi","attribute":"憐属性","fullName":"【桜の精との待ち合わせ】千寿暦","id":"141590","name":"桜の精との待ち合わせ","num":2,"rarity":4},{"actor":"ラモーナ・ウォルフ","actorRomanization":"Ramona Wolf","attribute":"憐属性","fullName":"【次の春まで別たれて】ラモーナ・ウォルフ","id":"141600","name":"次の春まで別たれて","num":2,"rarity":4},{"actor":"萬容","actorRomanization":"Yorozu Iruru","attribute":"憐属性","fullName":"【良妻は慈母の視線を向ける】萬容","id":"141610","name":"良妻は慈母の視線を向ける","num":2,"rarity":4},{"actor":"筆島しぐれ","actorRomanization":"Fudeshima Shigure","attribute":"憐属性","fullName":"【真実は数奇かつ残酷で】筆島しぐれ","id":"141620","name":"真実は数奇かつ残酷で","num":2,"rarity":4},{"actor":"カトリナ・グリーベル","actorRomanization":"Kathrina Griebel","attribute":"彩属性","fullName":"【妖精は花園で舞って】カトリナ・グリーベル","id":"141630","name":"妖精は花園で舞って","num":2,"rarity":4},{"actor":"柳場ぱんだ","actorRomanization":"Yanagiba Panda","attribute":"彩属性","fullName":"【空を自由に！】柳場ぱんだ","id":"141640","name":"空を自由に！","num":2,"rarity":4},{"actor":"連尺野初魅","actorRomanization":"Renjakuno Hatsumi","attribute":"陽属性","fullName":"【燃え尽きぬ復讐の炎】連尺野初魅","id":"141650","name":"燃え尽きぬ復讐の炎","num":2,"rarity":4},{"actor":"烏森大黒","actorRomanization":"Karasumori Daikoku","attribute":"陽属性","fullName":"【夢現に絡めとられて】烏森大黒","id":"141660","name":"夢現に絡めとられて","num":2,"rarity":4},{"actor":"王雪","actorRomanization":"Wang Xue","attribute":"憐属性","fullName":"【調合が味の秘訣】王雪","id":"141670","name":"調合が味の秘訣","num":2,"rarity":4},{"actor":"与那国緋花里","actorRomanization":"Yonaguni Hikari","attribute":"憐属性","fullName":"【マジカル・ティーサーブ！】与那国緋花里","id":"141680","name":"マジカル・ティーサーブ！","num":2,"rarity":4},{"actor":"連尺野初魅","actorRomanization":"Renjakuno Hatsumi","attribute":"凛属性","fullName":"【賢王は泰平を見る】連尺野初魅","id":"141690","name":"賢王は泰平を見る","num":2,"rarity":4},{"actor":"舎人仁花子","actorRomanization":"Toneri Nikako","attribute":"凛属性","fullName":"【摂政は謎を読み解いて】舎人仁花子","id":"141700","name":"摂政は謎を読み解いて","num":2,"rarity":4},{"actor":"静香","actorRomanization":" Shizuka","attribute":"陽属性","fullName":"【ロイヤル・ウェディング！】静香","id":"141710","name":"ロイヤル・ウェディング！","num":2,"rarity":4},{"actor":"白丸美兎","actorRomanization":"Shiromaru Mito","attribute":"陽属性","fullName":"【バラ園の中、花嫁は笑う】白丸美兎","id":"141720","name":"バラ園の中、花嫁は笑う","num":2,"rarity":4}]