[
    {
        "EventStoryListFlags" : 2,
        "Id" : 20001,
        "IsKeyStory" : true,
        "ListedStartDate" : "2023-08-10 17:00:00",
        "StoryEventMasterId" : 20001,
        "StoryMasterId" : 20001
    },
    {
        "EventStoryListFlags" : 8,
        "Id" : 20002,
        "IsKeyStory" : false,
        "ListedStartDate" : "2023-08-20 17:00:00",
        "StoryEventMasterId" : 20002,
        "StoryMasterId" : 20002
    },
    {
        "EventStoryListFlags" : 1,
        "Id" : 20003,
        "IsKeyStory" : false,
        "ListedStartDate" : "2023-08-31 17:00:00",
        "StoryEventMasterId" : 20003,
        "StoryMasterId" : 20003
    },
    {
        "EventStoryListFlags" : 4,
        "Id" : 20004,
        "IsKeyStory" : false,
        "ListedStartDate" : "2023-09-10 17:00:00",
        "StoryEventMasterId" : 20004,
        "StoryMasterId" : 20004
    },
    {
        "EventStoryListFlags" : 8,
        "Id" : 20005,
        "IsKeyStory" : true,
        "ListedStartDate" : "2023-09-20 17:00:00",
        "StoryEventMasterId" : 20005,
        "StoryMasterId" : 20005
    },
    {
        "EventStoryListFlags" : 3,
        "Id" : 20006,
        "IsKeyStory" : false,
        "ListedStartDate" : "2023-09-30 17:00:00",
        "StoryEventMasterId" : 20006,
        "StoryMasterId" : 20006
    },
    {
        "EventStoryListFlags" : 6,
        "Id" : 20007,
        "IsKeyStory" : true,
        "ListedStartDate" : "2023-10-10 17:00:00",
        "StoryEventMasterId" : 20007,
        "StoryMasterId" : 20007
    },
    {
        "EventStoryListFlags" : 13,
        "Id" : 20008,
        "IsKeyStory" : false,
        "ListedStartDate" : "2023-10-20 17:00:00",
        "StoryEventMasterId" : 20008,
        "StoryMasterId" : 20008
    },
    {
        "EventStoryListFlags" : 1,
        "Id" : 20009,
        "IsKeyStory" : false,
        "ListedStartDate" : "2023-11-10 17:00:00",
        "StoryEventMasterId" : 20009,
        "StoryMasterId" : 20009
    },
    {
        "EventStoryListFlags" : 8,
        "Id" : 20010,
        "IsKeyStory" : false,
        "ListedStartDate" : "2023-10-31 17:00:00",
        "StoryEventMasterId" : 20010,
        "StoryMasterId" : 20010
    },
    {
        "EventStoryListFlags" : 4,
        "Id" : 20011,
        "IsKeyStory" : false,
        "ListedStartDate" : "2023-11-30 17:00:00",
        "StoryEventMasterId" : 20011,
        "StoryMasterId" : 20011
    },
    {
        "EventStoryListFlags" : 11,
        "Id" : 20012,
        "IsKeyStory" : false,
        "ListedStartDate" : "2023-11-20 17:00:00",
        "StoryEventMasterId" : 20012,
        "StoryMasterId" : 20012
    }
]